cli_tables/__init__.py
cli_tables/cli_tables.py
cli_tables/gui.py
cli_tables-0.0.2.dist-info/LICENSE
cli_tables-0.0.2.dist-info/METADATA
cli_tables-0.0.2.dist-info/WHEEL
cli_tables-0.0.2.dist-info/top_level.txt
cli_tables-0.0.2.dist-info/RECORD
