Metadata-Version: 2.1
Name: cli-tables
Version: 0.0.2
Summary: Create pretty looking ascii tables
Home-page: https://github.com/thanosgn/cli-tables
Author: Thanos Giannooulos
Author-email: thanosgn@gmail.com
License: UNKNOWN
Platform: UNKNOWN
Classifier: Programming Language :: Python :: 2
Classifier: Programming Language :: Python :: 3
Classifier: License :: OSI Approved :: MIT License
Classifier: Operating System :: OS Independent
